lswmi/__init__.py
lswmi/__main__.py
lswmi/device.py
lswmi/main.py
lswmi/py.typed
lswmi-1.2.0.dist-info/METADATA
lswmi-1.2.0.dist-info/WHEEL
lswmi-1.2.0.dist-info/entry_points.txt
lswmi-1.2.0.dist-info/licenses/LICENSE
lswmi-1.2.0.dist-info/RECORD
