Metadata-Version: 2.1
Name: lswmi
Version: 1.2.0
Summary: Utility to retrieve information about WMI devices on Linux
Project-URL: Repository, https://github.com/Wer-Wolf/lswmi
Project-URL: Bugtracker, https://github.com/Wer-Wolf/lswmi/issues
Author-email: Armin Wolf <W_Armin@gmx.de>
License-File: LICENSE
Keywords: ACPI,WMI
Classifier: Environment :: Console
Classifier: Intended Audience :: Developers
Classifier: License :: OSI Approved :: GNU General Public License v2 or later (GPLv2+)
Classifier: Operating System :: POSIX :: Linux
Classifier: Programming Language :: Python :: 3 :: Only
Classifier: Topic :: System :: Hardware
Classifier: Topic :: Utilities
Classifier: Typing :: Typed
Requires-Python: >=3.11
